dnv/__init__.py
dnv/hydrod/__init__.py
dnv/hydrod/load_assemblies.py
dnv/hydrod/runtimeconfig.json
dnv/hydrod/workspace_utils.py
dnv/hydrod/.dlls/DNV.ApplicationVersionManager.Core.dll
dnv_hydrod-1.0.3rc50.dist-info/licenses/LICENSE
dnv_hydrod-1.0.3rc50.dist-info/METADATA
dnv_hydrod-1.0.3rc50.dist-info/WHEEL
dnv_hydrod-1.0.3rc50.dist-info/top_level.txt
dnv_hydrod-1.0.3rc50.dist-info/RECORD
