Metadata-Version: 2.4
Name: dnv-hydrod
Version: 1.0.3rc50
Summary: Python library for working with DNV HydroD workspaces and workflows.
Author-email: DNV <software.support@dnv.com>
Project-URL: Homepage, https://sesam.dnv.com
Keywords: hydrod,dnv,workflow,hydrodynamics
Classifier: Development Status :: 4 - Beta
Classifier: License :: OSI Approved :: MIT License
Classifier: Programming Language :: Python
Classifier: Programming Language :: Python :: 3.10
Requires-Python: <3.14,>=3.10
License-File: LICENSE
Requires-Dist: pythonnet==3.0.5
Dynamic: license-file
